adaptive_dbscan-0.3.2.dist-info/licenses/LICENSE
dadbscan/__init__.py
dadbscan/clustering.py
dadbscan/density.py
adaptive_dbscan-0.3.2.dist-info/METADATA
adaptive_dbscan-0.3.2.dist-info/WHEEL
adaptive_dbscan-0.3.2.dist-info/top_level.txt
adaptive_dbscan-0.3.2.dist-info/RECORD
