Metadata-Version: 2.4
Name: adaptive-dbscan
Version: 0.3.2
Summary: A python package for density adaptive DBSCAN clustering
Home-page: https://github.com/Sinamahani/AdaptiveDBSCAN
Author: Sina Sabermahani
Author-email: sina.sabermahani@gmail.com
License: MIT
License-File: LICENSE
Requires-Dist: numpy>=1.26.0
Requires-Dist: geopandas>=0.14.0
Requires-Dist: pandas>=2.1.1
Requires-Dist: matplotlib>=2.2.0
Requires-Dist: pyproj>=3.6.1
Requires-Dist: scipy>=1.11.3
Dynamic: author
Dynamic: author-email
Dynamic: description
Dynamic: description-content-type
Dynamic: home-page
Dynamic: license
Dynamic: license-file
Dynamic: requires-dist
Dynamic: summary
